{
  "id": "ELIOJXwcjZ-eTgLM9KgXR",
  "name": "Login to dashboard",
  "projectId": "640ee2a26ead56231ce8350b",
  "gitBranchName": "master",
  "services": [
    {
      "type": "1",
      "command": {
        "type": "2",
        "attributes": {
          "fromWidgetId": "ToYeAGfmf_781OJ1P9ap3",
          "nextWidgetId": "Ws3ZkRrrMU9jMz6BXyoUr",
          "gridRadioValue": "Screen",
          "selectedObjectBindingKey": "selectedObject",
          "editableForm": false
        }
      }
    }
  ],
  "_id": "irfjeEk_Frg3-EJU-gu-y",
  "updatedAt": "3/15/2023",
  "createdAt": "3/15/2023",
  "createdBy": "muzzamil",
  "updatedBy": "muzzamil"
}
