{
  "id": "ZTeihyi0Rxpirm7jtuirt",
  "name": "NAVIGATE_TO_DASHBOARD",
  "projectId": "640ee2a26ead56231ce8350b",
  "gitBranchName": "master",
  "services": [
    {
      "type": "1",
      "command": {
        "type": "3",
        "attributes": {
          "nextWidgetId": "bEhlV4JOC_0uSKBe2Wipq",
          "gridRadioValue": "",
          "selectedObjectBindingKey": "selectedObject",
          "editableForm": false
        }
      }
    }
  ],
  "csrf": "0.p0t6zda11yQ_xAK2i0dt-NuKlahIDC-",
  "_id": "YWi7u3ByQUxqIsGbkVpHH",
  "updatedAt": "9/27/2023",
  "createdAt": "9/27/2023",
  "createdBy": "muhammad.asad",
  "updatedBy": "muhammad.asad"
}
