{
  "id": "qKM1fin0Xo495U1AGBbzA",
  "_id": "WwP0iLw_auyQFdgdMY3el",
  "name": "NAVIGATE LOGIN TO OTP SCREEN TRIGGER",
  "old_name": "NAVIGATE LOGIN TO OTP SCREEN TRIGGER",
  "projectId": "640ee2a26ead56231ce8350b",
  "gitBranchName": "master",
  "services": [
    {
      "type": "1",
      "command": {
        "type": "2",
        "attributes": {
          "fromWidgetId": "kn-g6dLXYigHhX9bj8Z88",
          "nextWidgetId": "HfY_DDCxiRrfzbgB_HFS-",
          "gridRadioValue": "Screen",
          "selectedObjectBindingKey": "selectedObject",
          "editableForm": false
        }
      }
    }
  ],
  "csrf": "0.1w8csehs27ufUAHlyRr149194ulrbbRM",
  "updatedAt": "8/25/2023",
  "createdAt": "8/25/2023",
  "createdBy": "masood",
  "updatedBy": "masood"
}
