{
  "id": "gk24TY2fCgwJq0mnC3zIK",
  "_id": "FleVTcICv0GRZ2iA_h5bv",
  "name": "swap back to login",
  "old_name": "swap back to login",
  "projectId": "640ee2a26ead56231ce8350b",
  "gitBranchName": "master",
  "services": [
    {
      "type": "1",
      "command": {
        "type": "2",
        "attributes": {
          "fromWidgetId": "mK4y08W993cLc0exJT9x7",
          "nextWidgetId": "V5vD3FLZfZOY9b0wYhHGW",
          "gridRadioValue": "Screen",
          "selectedObjectBindingKey": "selectedObject",
          "editableForm": false
        }
      }
    }
  ],
  "csrf": "0.3fi6ozzg76enlerHSjsndTek2OuYLRTE",
  "updatedAt": "7/24/2024",
  "createdAt": "7/24/2024",
  "createdBy": "masood",
  "updatedBy": "masood"
}
