{
  "id": "L8sUHndGEv4Tepwpup75y",
  "name": "ZakatConfirm_TO_Receipt_Trigger",
  "projectId": "640ee2a26ead56231ce8350b",
  "gitBranchName": "master",
  "services": [
    {
      "type": "1",
      "command": {
        "type": "3",
        "attributes": {
          "nextWidgetId": "Ltmd1byn5g7dH3qbiz24B",
          "gridRadioValue": "",
          "selectedObjectBindingKey": "selectedObject",
          "editableForm": false
        }
      }
    }
  ],
  "csrf": "0.f68q4q0gvmrtDrkSZb_ec_BYzmMTGby",
  "_id": "y_shbcg6DZayKvDpLT2gb",
  "updatedAt": "9/25/2023",
  "createdAt": "9/25/2023",
  "createdBy": "muhammad.asad",
  "updatedBy": "muhammad.asad"
}
